{
    "image_path": "filtered_colums_from_raw\\filtered_Ficha2_1_colum1_5.jpg",
    "fingerprints": [
        {
            "x": 12,
            "yi": 105,
            "yf": 335,
            "w": 338,
            "color": "red"
        },
        {
            "x": 12,
            "yi": 335,
            "yf": 548,
            "w": 338,
            "color": "red"
        },
        {
            "x": 10,
            "yi": 548,
            "yf": 755,
            "w": 340,
            "color": "red"
        },
        {
            "x": 20,
            "yi": 758,
            "yf": 969,
            "w": 225,
            "color": "green"
        },
        {
            "x": 15,
            "yi": 969,
            "yf": 1137,
            "w": 225,
            "color": "green"
        }
    ]
}